{"cameraMode":{"drawMode":0,"name":"Shaded","section":"Shading Mode"},"sceneLighting":true,"audioPlay":false,"sceneViewState":{"showFog":true,"showMaterialUpdate":false,"showSkybox":true,"showFlares":true,"showImageEffects":true,"showParticleSystems":true},"in2DMode":false,"pivot":{"x":77.59332275390625,"y":11.938495635986329,"z":2.7611091136932375},"rotation":{"x":0.19784075021743775,"y":-0.1420636624097824,"z":0.02899172157049179,"w":0.9694516658782959},"size":1123.679931640625,"orthographic":false}